twitchbot/__init__.py
twitchbot/api/__init__.py
twitchbot/api/cache.py
twitchbot/api/client.py
twitchbot/api/game.py
twitchbot/api/helix.py
twitchbot/api/kraken.py
twitchbot/api/stream.py
twitchbot/api/user.py
twitchbot/bot/__init__.py
twitchbot/bot/bot.py
twitchbot/bot/cache.py
twitchbot/bot/check.py
twitchbot/bot/command.py
twitchbot/bot/context.py
twitchbot/bot/converter.py
twitchbot/bot/event.py
twitchbot/bot/game.py
twitchbot/bot/interval.py
twitchbot/bot/stream.py
twitchbot/bot/user.py
twitchbot/irc/__init__.py
twitchbot/irc/client.py
twitchbot/irc/message.py
twitchbot/irc/twitch_client.py
twitchbot-0.1.0.dev61.dist-info/LICENSE
twitchbot-0.1.0.dev61.dist-info/METADATA
twitchbot-0.1.0.dev61.dist-info/WHEEL
twitchbot-0.1.0.dev61.dist-info/top_level.txt
twitchbot-0.1.0.dev61.dist-info/RECORD
